substring/__init__.py
substring/substring.py
substring/testing.py
substring-0.2.dist-info/METADATA
substring-0.2.dist-info/RECORD
substring-0.2.dist-info/WHEEL
substring-0.2.dist-info/top_level.txt
